{"mehdy/anbar": [], "mehdy/pyeez": [], "iconsbox/icons": [], "justmisam/leitner": [], "justmisam/lmq": [], "justmisam/PyLMQ": [], "loreanvictor/tyfon": [], "loreanvictor/callbag-jsx": [], "divar-ir/divar-starter-kit": [], "mehdipourfar/webp-server": [], "alisinabh/paperify": [], "imaNNeoFighT/fl_chart": [], "anvaari/BarnameKon": [], "shayanh/grpc-go-contracts": [], "erfaniaa/text-to-commit-history": [], "erfaniaa/thatcher-effect-dataset-generator": [], "Mariotek/javascript-persian-interview-questions": [], "Mariotek/reactjs-persian-interview-questions": [], "moharnadreza/jsonplaceholder": [], "zarbchain/zarb-go": [], "ajangi/php-rest-response": [], "ajangi/laravel-crypt-model": [], "ajangi/gogit": [], "martianboy/peanar": [], "mehdizarepour/gato": [], "mehdizarepour/text-style-editor": [], "mehdizarepour/instagram-text-editor": [], "mehdizarepour/flutter-global-configs": [], "evryn/laravel-toman": [], "cafebazaar/keepalived-exporter": [], "nainemom/win7": []}